ncrar_audio/__init__.py
ncrar_audio/babyface.py
ncrar_audio/cpod.py
ncrar_audio/dante.py
ncrar_audio/osc_client.py
ncrar_audio/sound_device.py
ncrar_audio/totalmix_fx_volume_map.json
ncrar_audio/triggers.py
ncrar_audio/version.py
ncrar_audio/io/__init__.py
ncrar_audio/io/ihs/__init__.py
ncrar_audio/io/ihs/cam.py
ncrar_audio/io/ihs/stm.py
ncrar_audio-0.3.9.dist-info/LICENSE.txt
ncrar_audio-0.3.9.dist-info/METADATA
ncrar_audio-0.3.9.dist-info/WHEEL
ncrar_audio-0.3.9.dist-info/top_level.txt
ncrar_audio-0.3.9.dist-info/RECORD
