Metadata-Version: 2.2
Name: ncrar-audio
Version: 0.3.9
Summary: Audio tools supporting psiexperiment
Author-email: "Buran Consulting, LLC" <info@bradburan.com>
Maintainer-email: "Buran Consulting, LLC" <info@bradburan.com>
Requires-Python: >=3.7
License-File: LICENSE.txt
Requires-Dist: numpy
Requires-Dist: scipy
Requires-Dist: pandas
Requires-Dist: psiaudio
Requires-Dist: python-osc
Requires-Dist: sounddevice
Provides-Extra: docs
Requires-Dist: sphinx; extra == "docs"
Requires-Dist: pydata_sphinx_theme; extra == "docs"
Requires-Dist: pygments-enaml; extra == "docs"
Requires-Dist: sphinx-autobuild; extra == "docs"
Requires-Dist: sphinxcontrib-apidoc; extra == "docs"
Requires-Dist: sphinx-gallery; extra == "docs"
Provides-Extra: test
Requires-Dist: pytest; extra == "test"
Requires-Dist: pytest-benchmark; extra == "test"
Provides-Extra: examples
Requires-Dist: psiaudio; extra == "examples"
Requires-Dist: matplotlib; extra == "examples"
